{
  "names": {
    "John": {
      "use_count": 5,
      "last_used": "2025-11-21T22:50:12",
      "disabled": false
    },
    "Sarah": {
      "use_count": 5,
      "last_used": "2025-11-21T22:50:12",
      "disabled": false
    },
    "Michael": {
      "use_count": 5,
      "last_used": "2025-11-21T22:50:12",
      "disabled": false
    },
    "Emily": {
      "use_count": 5,
      "last_used": "2025-11-21T23:08:24",
      "disabled": false
    },
    "David": {
      "use_count": 5,
      "last_used": "2025-11-21T23:08:24",
      "disabled": false
    },
    "Sophia": {
      "use_count": 5,
      "last_used": "2025-11-21T23:08:24",
      "disabled": false
    },
    "Daniel": {
      "use_count": 5,
      "last_used": "2025-11-21T23:08:24",
      "disabled": false
    },
    "Olivia": {
      "use_count": 5,
      "last_used": "2025-11-21T23:13:12",
      "disabled": false
    },
    "Matthew": {
      "use_count": 5,
      "last_used": "2025-11-21T23:13:12",
      "disabled": false
    },
    "Isabella": {
      "use_count": 5,
      "last_used": "2025-11-21T23:13:12",
      "disabled": false
    },
    "James": {
      "use_count": 5,
      "last_used": "2025-11-21T23:13:12",
      "disabled": false
    },
    "Ava": {
      "use_count": 4,
      "last_used": "2025-11-21T22:42:13",
      "disabled": false
    },
    "Liam": {
      "use_count": 4,
      "last_used": "2025-11-21T22:42:13",
      "disabled": false
    },
    "Mia": {
      "use_count": 4,
      "last_used": "2025-11-21T22:42:13",
      "disabled": false
    },
    "Noah": {
      "use_count": 4,
      "last_used": "2025-11-21T22:42:13",
      "disabled": false
    },
    "Charlotte": {
      "use_count": 4,
      "last_used": "2025-11-21T22:50:11",
      "disabled": false
    }
  },
  "developers": {
    "Hilton": {
      "use_count": 6,
      "last_used": "2025-11-21T23:08:24",
      "disabled": false
    },
    "Marriott": {
      "use_count": 6,
      "last_used": "2025-11-21T23:13:12",
      "disabled": false
    },
    "Wyndham": {
      "use_count": 6,
      "last_used": "2025-11-21T23:13:12",
      "disabled": false
    },
    "Holiday Inn": {
      "use_count": 6,
      "last_used": "2025-11-21T23:13:12",
      "disabled": false
    },
    "Diamond Resorts": {
      "use_count": 6,
      "last_used": "2025-11-21T23:13:12",
      "disabled": false
    },
    "Westgate": {
      "use_count": 5,
      "last_used": "2025-11-21T22:42:13",
      "disabled": false
    },
    "Bluegreen Vacations": {
      "use_count": 5,
      "last_used": "2025-11-21T22:42:13",
      "disabled": false
    },
    "Ritz Carlton": {
      "use_count": 5,
      "last_used": "2025-11-21T22:50:12",
      "disabled": false
    },
    "Four Seasons": {
      "use_count": 5,
      "last_used": "2025-11-21T22:50:12",
      "disabled": false
    },
    "Sheraton": {
      "use_count": 5,
      "last_used": "2025-11-21T22:50:12",
      "disabled": false
    },
    "Hyatt": {
      "use_count": 5,
      "last_used": "2025-11-21T22:50:12",
      "disabled": false
    },
    "Accor": {
      "use_count": 5,
      "last_used": "2025-11-21T23:08:24",
      "disabled": false
    },
    "Best Western": {
      "use_count": 5,
      "last_used": "2025-11-21T23:08:24",
      "disabled": false
    },
    "Radisson": {
      "use_count": 5,
      "last_used": "2025-11-21T23:08:24",
      "disabled": false
    }
  },
  "_meta": {
    "total_names": 16,
    "total_developers": 14,
    "last_update": "2025-11-21T23:13:12"
  }
}